parler_rest/__init__.py
parler_rest/fields.py
parler_rest/serializers.py
parler_rest/utils.py
django_parler_rest-2.2.dist-info/AUTHORS.md
django_parler_rest-2.2.dist-info/LICENSE
django_parler_rest-2.2.dist-info/METADATA
django_parler_rest-2.2.dist-info/WHEEL
django_parler_rest-2.2.dist-info/top_level.txt
django_parler_rest-2.2.dist-info/RECORD
