Metadata-Version: 2.1
Name: django-parler-rest
Version: 2.2
Summary: Multilingual support for django-rest-framework
Home-page: https://github.com/edoburu/django-parler-rest
Download-URL: https://github.com/edoburu/django-parler-rest/zipball/master
Author: Diederik van der Boor
Author-email: opensource@edoburu.nl
License: Apache 2.0
Platform: UNKNOWN
Classifier: Development Status :: 5 - Production/Stable
Classifier: Environment :: Web Environment
Classifier: Framework :: Django
Classifier: Intended Audience :: Developers
Classifier: License :: OSI Approved :: Apache Software License
Classifier: Operating System :: OS Independent
Classifier: Programming Language :: Python
Classifier: Programming Language :: Python :: 3.8
Classifier: Programming Language :: Python :: 3.9
Classifier: Programming Language :: Python :: 3.10
Classifier: Framework :: Django :: 2.2
Classifier: Framework :: Django :: 3.2
Classifier: Framework :: Django :: 4.0
License-File: LICENSE
License-File: AUTHORS.md
